Metadata-Version: 1.0
Name: transformers-nfota
Version: 0.5
Summary: Various Transformer Models
Home-page: UNKNOWN
Author: UNKNOWN
Author-email: UNKNOWN
License: UNKNOWN
Platform: UNKNOWN
